LICENSE
MANIFEST.in
README.rst
requirements.txt
setup.cfg
setup.py
bin/pagrant
pagrant/__init__.py
pagrant/basecommand.py
pagrant/cmdoptions.py
pagrant/cmdparser.py
pagrant/environment.py
pagrant/exceptions.py
pagrant/fab.py
pagrant/globalsettings.py
pagrant/importer.py
pagrant/log.py
pagrant/machine.py
pagrant/main.py
pagrant/pagrantfile.py
pagrant/process.py
pagrant/util.py
pagrant/version.py
pagrant.egg-info/PKG-INFO
pagrant.egg-info/SOURCES.txt
pagrant.egg-info/dependency_links.txt
pagrant.egg-info/requires.txt
pagrant.egg-info/top_level.txt
pagrant/ci/__init__.py
pagrant/ci/jenkins/__init__.py
pagrant/ci/teamcity/__init__.py
pagrant/ci/teamcity/tc.py
pagrant/commands/__init__.py
pagrant/commands/clean.py
pagrant/commands/deploy.py
pagrant/commands/init.py
pagrant/commands/test.py
pagrant/commands/vmp/__init__.py
pagrant/commands/vmp/install.py
pagrant/commands/vmp/list.py
pagrant/commands/vmp/remove.py
pagrant/provisioners/__init__.py
pagrant/provisioners/health/__init__.py
pagrant/provisioners/health/http.py
pagrant/provisioners/puppet/__init__.py
pagrant/provisioners/web/__init__.py
pagrant/provisioners/web/tomcat.py
pagrant/templates/Pagrantfile.py
pagrant/templates/__init__.py
pagrant/test/__init__.py
pagrant/vendors/__init__.py
pagrant/vendors/docker/__init__.py
pagrant/vendors/docker/client.py
pagrant/vendors/docker/auth/__init__.py
pagrant/vendors/docker/auth/auth.py
pagrant/vendors/docker/unixconn/__init__.py
pagrant/vendors/docker/unixconn/unixconn.py
pagrant/vendors/docker/utils/__init__.py
pagrant/vendors/docker/utils/utils.py
pagrant/vendors/lxclite/__init__.py
pagrant/vendors/myoptparser/__init__.py
pagrant/vendors/myoptparser/optparse.py
pagrant/vmproviders/__init__.py
pagrant/vmproviders/docker/__init__.py
pagrant/vmproviders/docker/actions.py
pagrant/vmproviders/lxc/__init__.py
pagrant/vmproviders/lxc/actions.py
test/pkg_test/__init__.py
test/pkg_test/pkg.py