Metadata-Version: 1.1
Name: pagrant
Version: 1.0.4
Summary: a distributed test framework
Home-page: https://github.com/markshao/pagrant
Author: markshao,xiaobo
Author-email: mark.shao@emc.com
License: MIT
Keywords: framework nose testing
Platform: any
Classifier: Programming Language :: Python
